moberg_analytics_hdf5/__init__.py
moberg_analytics_hdf5/hdf5_exceptions.py
moberg_analytics_hdf5/hdf5_tools.py
moberg_analytics_hdf5/moberg_hdf5.py
Moberg_Analytics_HDF5-1.0.1.dist-info/METADATA
Moberg_Analytics_HDF5-1.0.1.dist-info/WHEEL
Moberg_Analytics_HDF5-1.0.1.dist-info/top_level.txt
Moberg_Analytics_HDF5-1.0.1.dist-info/RECORD
