Metadata-Version: 2.1
Name: Moberg-Analytics-HDF5
Version: 1.0.1
Summary: Moberg Analytics HDF5 Functions
Home-page: https://github.com/Moberg-Analytics-Inc/Moberg-Analytics-HDF5
Author: Moberg Analytics
Author-email: zack.goldblum@moberganalytics.com
License: MIT
Platform: UNKNOWN
Classifier: License :: OSI Approved :: MIT License
Classifier: Programming Language :: Python :: 3
Classifier: Programming Language :: Python :: 3.9
Requires-Dist: h5py
Requires-Dist: numpy
Requires-Dist: pandas
